MANIFEST.in
README.rst
environment.yml
pkg_conf.py
setup.py
conda-recipe/bld.bat
conda-recipe/build.sh
conda-recipe/meta.yaml
numpy_indexed/__init__.py
numpy_indexed/arraysetops.py
numpy_indexed/examples.py
numpy_indexed/funcs.py
numpy_indexed/grouping.py
numpy_indexed/index.py
numpy_indexed/monkey_patch.py
numpy_indexed/semantics.py
numpy_indexed/utility.py
numpy_indexed.egg-info/PKG-INFO
numpy_indexed.egg-info/SOURCES.txt
numpy_indexed.egg-info/dependency_links.txt
numpy_indexed.egg-info/requires.txt
numpy_indexed.egg-info/top_level.txt
numpy_indexed/tests/__init__.py
numpy_indexed/tests/test_indexed.py
numpy_indexed/tests/test_numpy.py