Metadata-Version: 1.1
Name: numpy-indexed
Version: 0.2.19
Summary: Numpy extensions for set operations on nd-arrays, group_by operations, and related functionality
Home-page: https://github.com/EelcoHoogendoorn/Numpy_arraysetops_EP
Author: Eelco Hoogendoorn
Author-email: hoogendoorn.eelco@gmail.com
License: Freely Distributable
Keywords: numpy group_by set-operations indexing
Platform: any
Classifier: Development Status :: 4 - Beta
Classifier: Intended Audience :: Science/Research
Classifier: Intended Audience :: Developers
Classifier: Topic :: Utilities
Classifier: Topic :: Scientific/Engineering
Classifier: License :: Freely Distributable
Classifier: Operating System :: MacOS :: MacOS X
Classifier: Operating System :: Microsoft :: Windows
Classifier: Operating System :: POSIX
Classifier: Programming Language :: Python
Classifier: Programming Language :: Python :: 2.7
Classifier: Programming Language :: Python :: 3.5
